{"data": [
    {
    "id": 0,
    "title": "Read for 30 minutes",
    "day": {
        "mon": "Incomplete",
        "tue": "Incomplete",
        "wed": "Incomplete",
        "thu": "Incomplete",
        "fri": "Incomplete",
        "sat": "Incomplete",
        "sun": "Incomplete"
    }
    },
    {
        "id": 1,
        "title": "Run a mile",
        "day": {
            "mon": "Incomplete",
            "tue": "Incomplete",
            "wed": "Incomplete",
            "thu": "Incomplete",
            "fri": "Incomplete",
            "sat": "Incomplete",
            "sun": "Incomplete"
        }
    }
]} 